{
    "Thoughtseize": {
      "cardname": "Thoughtseize",
      "mainboard": {
        "decks": 0.405,
        "avg": 4.0
      },
      "sideboard": {
        "decks": 0,
        "avg": 0
      }
    },
    "Takenuma, Abandoned Mire": {
      "cardname": "Takenuma, Abandoned Mire",
      "mainboard": {
        "decks": 0.396,
        "avg": 1.0
      },
      "sideboard": {
        "decks": 0,
        "avg": 0
      }
    },
    "Concealed Courtyard": {
      "cardname": "Concealed Courtyard",
      "mainboard": {
        "decks": 0.37,
        "avg": 3.9
      },
      "sideboard": {
        "decks": 0,
        "avg": 0
      }
    },
    "Godless Shrine": {
      "cardname": "Godless Shrine",
      "mainboard": {
        "decks": 0.37,
        "avg": 2.2
      },
      "sideboard": {
        "decks": 0,
        "avg": 0
      }
    },
    "Boseiju, Who Endures": {
      "cardname": "Boseiju, Who Endures",
      "mainboard": {
        "decks": 0.366,
        "avg": 1.3
      },
      "sideboard": {
        "decks": 0,
        "avg": 0
      }
    },
    "Greasefang, Okiba Boss": {
      "cardname": "Greasefang, Okiba Boss",
      "mainboard": {
        "decks": 0.304,
        "avg": 4.0
      },
      "sideboard": {
        "decks": 0,
        "avg": 0
      }
    },
    "Parhelion II": {
      "cardname": "Parhelion II",
      "mainboard": {
        "decks": 0.304,
        "avg": 4.0
      },
      "sideboard": {
        "decks": 0,
        "avg": 0
      }
    },
    "Blooming Marsh": {
      "cardname": "Blooming Marsh",
      "mainboard": {
        "decks": 0.295,
        "avg": 3.4
      },
      "sideboard": {
        "decks": 0,
        "avg": 0
      }
    },
    "Formidable Speaker": {
      "cardname": "Formidable Speaker",
      "mainboard": {
        "decks": 0.295,
        "avg": 3.9
      },
      "sideboard": {
        "decks": 0,
        "avg": 0
      }
    },
    "Otawara, Soaring City": {
      "cardname": "Otawara, Soaring City",
      "mainboard": {
        "decks": 0.278,
        "avg": 1.0
      },
      "sideboard": {
        "decks": 0,
        "avg": 0
      }
    },
    "Brushland": {
      "cardname": "Brushland",
      "mainboard": {
        "decks": 0.26,
        "avg": 1.5
      },
      "sideboard": {
        "decks": 0,
        "avg": 0
      }
    },
    "Temple Garden": {
      "cardname": "Temple Garden",
      "mainboard": {
        "decks": 0.26,
        "avg": 4.0
      },
      "sideboard": {
        "decks": 0,
        "avg": 0
      }
    },
    "Emptiness": {
      "cardname": "Emptiness",
      "mainboard": {
        "decks": 0.256,
        "avg": 1.2
      },
      "sideboard": {
        "decks": 0,
        "avg": 0
      }
    },
    "Monastery Swiftspear": {
      "cardname": "Monastery Swiftspear",
      "mainboard": {
        "decks": 0.238,
        "avg": 4.0
      },
      "sideboard": {
        "decks": 0,
        "avg": 0
      }
    },
    "Soul-Scar Mage": {
      "cardname": "Soul-Scar Mage",
      "mainboard": {
        "decks": 0.238,
        "avg": 4.0
      },
      "sideboard": {
        "decks": 0,
        "avg": 0
      }
    },
    "Burst Lightning": {
      "cardname": "Burst Lightning",
      "mainboard": {
        "decks": 0.233,
        "avg": 3.7
      },
      "sideboard": {
        "decks": 0,
        "avg": 0
      }
    },
    "Cache Grab": {
      "cardname": "Cache Grab",
      "mainboard": {
        "decks": 0.229,
        "avg": 3.1
      },
      "sideboard": {
        "decks": 0,
        "avg": 0
      }
    },
    "Bitter Triumph": {
      "cardname": "Bitter Triumph",
      "mainboard": {
        "decks": 0.22,
        "avg": 2.9
      },
      "sideboard": {
        "decks": 0.119,
        "avg": 1.8
      }
    },
    "Emberheart Challenger": {
      "cardname": "Emberheart Challenger",
      "mainboard": {
        "decks": 0.22,
        "avg": 3.8
      },
      "sideboard": {
        "decks": 0,
        "avg": 0
      }
    },
    "Reckless Rage": {
      "cardname": "Reckless Rage",
      "mainboard": {
        "decks": 0.22,
        "avg": 3.7
      },
      "sideboard": {
        "decks": 0,
        "avg": 0
      }
    },
    "Duress": {
      "cardname": "Duress",
      "mainboard": {
        "decks": 0,
        "avg": 0
      },
      "sideboard": {
        "decks": 0.383,
        "avg": 2.4
      }
    },
    "Pyroclasm": {
      "cardname": "Pyroclasm",
      "mainboard": {
        "decks": 0,
        "avg": 0
      },
      "sideboard": {
        "decks": 0.313,
        "avg": 2.5
      }
    },
    "Pest Control": {
      "cardname": "Pest Control",
      "mainboard": {
        "decks": 0,
        "avg": 0
      },
      "sideboard": {
        "decks": 0.308,
        "avg": 2.1
      }
    },
    "Vanishing Verse": {
      "cardname": "Vanishing Verse",
      "mainboard": {
        "decks": 0,
        "avg": 0
      },
      "sideboard": {
        "decks": 0.269,
        "avg": 2.0
      }
    },
    "Ashiok, Dream Render": {
      "cardname": "Ashiok, Dream Render",
      "mainboard": {
        "decks": 0,
        "avg": 0
      },
      "sideboard": {
        "decks": 0.233,
        "avg": 1.8
      }
    },
    "Fatal Push": {
      "cardname": "Fatal Push",
      "mainboard": {
        "decks": 0,
        "avg": 0
      },
      "sideboard": {
        "decks": 0.203,
        "avg": 2.8
      }
    },
    "High Noon": {
      "cardname": "High Noon",
      "mainboard": {
        "decks": 0,
        "avg": 0
      },
      "sideboard": {
        "decks": 0.203,
        "avg": 1.9
      }
    },
    "Soul-Guide Lantern": {
      "cardname": "Soul-Guide Lantern",
      "mainboard": {
        "decks": 0,
        "avg": 0
      },
      "sideboard": {
        "decks": 0.194,
        "avg": 2.2
      }
    },
    "Scorching Shot": {
      "cardname": "Scorching Shot",
      "mainboard": {
        "decks": 0,
        "avg": 0
      },
      "sideboard": {
        "decks": 0.189,
        "avg": 2.0
      }
    },
    "Loran of the Third Path": {
      "cardname": "Loran of the Third Path",
      "mainboard": {
        "decks": 0,
        "avg": 0
      },
      "sideboard": {
        "decks": 0.181,
        "avg": 1.1
      }
    },
    "Magebane Lizard": {
      "cardname": "Magebane Lizard",
      "mainboard": {
        "decks": 0,
        "avg": 0
      },
      "sideboard": {
        "decks": 0.176,
        "avg": 3.7
      }
    },
    "Redcap Melee": {
      "cardname": "Redcap Melee",
      "mainboard": {
        "decks": 0,
        "avg": 0
      },
      "sideboard": {
        "decks": 0.172,
        "avg": 2.1
      }
    },
    "Rest in Peace": {
      "cardname": "Rest in Peace",
      "mainboard": {
        "decks": 0,
        "avg": 0
      },
      "sideboard": {
        "decks": 0.167,
        "avg": 2.5
      }
    },
    "Sheoldred, the Apocalypse": {
      "cardname": "Sheoldred, the Apocalypse",
      "mainboard": {
        "decks": 0,
        "avg": 0
      },
      "sideboard": {
        "decks": 0.159,
        "avg": 1.0
      }
    },
    "Beza, the Bounding Spring": {
      "cardname": "Beza, the Bounding Spring",
      "mainboard": {
        "decks": 0,
        "avg": 0
      },
      "sideboard": {
        "decks": 0.15,
        "avg": 1.9
      }
    },
    "Voice of Victory": {
      "cardname": "Voice of Victory",
      "mainboard": {
        "decks": 0,
        "avg": 0
      },
      "sideboard": {
        "decks": 0.15,
        "avg": 1.0
      }
    },
    "Sunspine Lynx": {
      "cardname": "Sunspine Lynx",
      "mainboard": {
        "decks": 0,
        "avg": 0
      },
      "sideboard": {
        "decks": 0.141,
        "avg": 3.1
      }
    },
    "Doorkeeper Thrull": {
      "cardname": "Doorkeeper Thrull",
      "mainboard": {
        "decks": 0,
        "avg": 0
      },
      "sideboard": {
        "decks": 0.132,
        "avg": 3.0
      }
    },
    "Firebending Lesson": {
      "cardname": "Firebending Lesson",
      "mainboard": {
        "decks": 0,
        "avg": 0
      },
      "sideboard": {
        "decks": 0.123,
        "avg": 1.0
      }
    }
}
